[
  {
    "inputs": [
      {
        "internalType": "address",
        "name": "_ctiGovernance",
        "type": "address"
      },
      {
        "internalType": "address",
        "name": "_ctiUsers",
        "type": "address"
      },
      {
        "internalType": "address",
        "name": "_ctiToken",
        "type": "address"
      },
      {
        "internalType": "address",
        "name": "_proposerAddress",
        "type": "address"
      },
      {
        "internalType": "string",
        "name": "_ctiName",
        "type": "string"
      },
      {
        "internalType": "string",
        "name": "_ctiId",
        "type": "string"
      },
      {
        "internalType": "string",
        "name": "_ctiHash",
        "type": "string"
      },
      {
        "internalType": "uint256",
        "name": "_rewardTokenAmount",
        "type": "uint256"
      }
    ],
    "stateMutability": "nonpayable",
    "type": "constructor"
  },
  {
    "inputs": [
      {
        "internalType": "address",
        "name": "voter",
        "type": "address"
      }
    ],
    "name": "alreadyVotedByAddress",
    "outputs": [
      {
        "internalType": "enum CTI.VoteChoice",
        "name": "voteChoice",
        "type": "uint8"
      },
      {
        "internalType": "uint256",
        "name": "amount",
        "type": "uint256"
      },
      {
        "internalType": "bool",
        "name": "voted",
        "type": "bool"
      }
    ],
    "stateMutability": "view",
    "type": "function"
  },
  {
    "inputs": [],
    "name": "ctiGovernance",
    "outputs": [
      {
        "internalType": "contract ICtiGovernance",
        "name": "",
        "type": "address"
      }
    ],
    "stateMutability": "view",
    "type": "function"
  },
  {
    "inputs": [],
    "name": "ctiHash",
    "outputs": [
      {
        "internalType": "string",
        "name": "",
        "type": "string"
      }
    ],
    "stateMutability": "view",
    "type": "function"
  },
  {
    "inputs": [],
    "name": "ctiId",
    "outputs": [
      {
        "internalType": "string",
        "name": "",
        "type": "string"
      }
    ],
    "stateMutability": "view",
    "type": "function"
  },
  {
    "inputs": [],
    "name": "ctiName",
    "outputs": [
      {
        "internalType": "string",
        "name": "",
        "type": "string"
      }
    ],
    "stateMutability": "view",
    "type": "function"
  },
  {
    "inputs": [],
    "name": "ctiToken",
    "outputs": [
      {
        "internalType": "contract ERC20Burnable",
        "name": "",
        "type": "address"
      }
    ],
    "stateMutability": "view",
    "type": "function"
  },
  {
    "inputs": [],
    "name": "ctiUsers",
    "outputs": [
      {
        "internalType": "contract ICtiUsers",
        "name": "",
        "type": "address"
      }
    ],
    "stateMutability": "view",
    "type": "function"
  },
  {
    "inputs": [],
    "name": "expirationTime",
    "outputs": [
      {
        "internalType": "uint256",
        "name": "",
        "type": "uint256"
      }
    ],
    "stateMutability": "view",
    "type": "function"
  },
  {
    "inputs": [],
    "name": "proposerAddress",
    "outputs": [
      {
        "internalType": "address",
        "name": "",
        "type": "address"
      }
    ],
    "stateMutability": "view",
    "type": "function"
  },
  {
    "inputs": [],
    "name": "rewardTokenAmount",
    "outputs": [
      {
        "internalType": "uint256",
        "name": "",
        "type": "uint256"
      }
    ],
    "stateMutability": "view",
    "type": "function"
  },
  {
    "inputs": [],
    "name": "voteAmounts",
    "outputs": [
      {
        "internalType": "uint256",
        "name": "validAmount",
        "type": "uint256"
      },
      {
        "internalType": "uint256",
        "name": "invalidAmount",
        "type": "uint256"
      },
      {
        "internalType": "uint256",
        "name": "abstainAmount",
        "type": "uint256"
      }
    ],
    "stateMutability": "view",
    "type": "function"
  },
  {
    "inputs": [],
    "name": "voteStatus",
    "outputs": [
      {
        "internalType": "enum CTI.VoteStatusEnum",
        "name": "",
        "type": "uint8"
      }
    ],
    "stateMutability": "view",
    "type": "function"
  },
  {
    "inputs": [],
    "name": "votingDuration",
    "outputs": [
      {
        "internalType": "uint256",
        "name": "",
        "type": "uint256"
      }
    ],
    "stateMutability": "view",
    "type": "function"
  },
  {
    "inputs": [],
    "name": "valid",
    "outputs": [
      {
        "internalType": "bool",
        "name": "",
        "type": "bool"
      }
    ],
    "stateMutability": "nonpayable",
    "type": "function"
  },
  {
    "inputs": [],
    "name": "invalid",
    "outputs": [
      {
        "internalType": "bool",
        "name": "",
        "type": "bool"
      }
    ],
    "stateMutability": "nonpayable",
    "type": "function"
  },
  {
    "inputs": [],
    "name": "abstain",
    "outputs": [
      {
        "internalType": "bool",
        "name": "",
        "type": "bool"
      }
    ],
    "stateMutability": "nonpayable",
    "type": "function"
  },
  {
    "inputs": [],
    "name": "close",
    "outputs": [
      {
        "internalType": "bool",
        "name": "",
        "type": "bool"
      }
    ],
    "stateMutability": "nonpayable",
    "type": "function"
  }
]